rt_activation/__init__.py
rt_activation/activation_functions.py
rt_activation-1.0.0.dist-info/licenses/LICENSE
rt_activation-1.0.0.dist-info/METADATA
rt_activation-1.0.0.dist-info/WHEEL
rt_activation-1.0.0.dist-info/top_level.txt
rt_activation-1.0.0.dist-info/RECORD
