Metadata-Version: 2.4
Name: rt-activation
Version: 1.0.0
Summary: Rectified Tangent Activation (RTA) function for Keras/TensorFlow
Author-email: Gaurav Pandey <gaurav.pandey1812@gmail.com>
License: MIT
Project-URL: Homepage, https://github.com/gkp1812/rt-activation
Project-URL: Repository, https://github.com/gkp1812/rt-activation
Project-URL: Issues, https://github.com/gkp1812/rt-activation/issues
Keywords: keras,tensorflow,activation,neural-networks,deep-learning
Classifier: Development Status :: 4 - Beta
Classifier: Intended Audience :: Developers
Classifier: Intended Audience :: Science/Research
Classifier: License :: OSI Approved :: MIT License
Classifier: Operating System :: OS Independent
Classifier: Programming Language :: Python :: 3
Classifier: Programming Language :: Python :: 3.8
Classifier: Programming Language :: Python :: 3.9
Classifier: Programming Language :: Python :: 3.10
Classifier: Programming Language :: Python :: 3.11
Classifier: Programming Language :: Python :: 3.12
Classifier: Topic :: Scientific/Engineering :: Artificial Intelligence
Classifier: Topic :: Software Development :: Libraries :: Python Modules
Requires-Python: >=3.8
License-File: LICENSE
Requires-Dist: keras>=3.0.0
Provides-Extra: dev
Requires-Dist: pytest>=6.0; extra == "dev"
Requires-Dist: pytest-cov; extra == "dev"
Requires-Dist: black; extra == "dev"
Requires-Dist: flake8; extra == "dev"
Requires-Dist: mypy; extra == "dev"
Dynamic: license-file
